{
  "title": "Immortal, invisible, God only wise",
  "author": "",
  "tune": "Joanna",
  "number": "35",
  "lyrics": "Immortal, invisible, God only wise,\nIn light inaccessible hid from our eyes,\nMost blessed, most glorious, the Ancient of Days,\nAlmighty, victorious, thy great Name we praise.\n\nUnresting, unhasting, and silent as light,\nNor wanting, nor wasting, thou rulest in might;\nThy justice like mountains high soaring above\nThy clouds which are fountains of goodness and love.\n\nGreat Father of Glory, pure Father of Light,\nThine angels adore thee, all veiling their sight;\nAll praise we would render; O help us to see\n'Tis only the splendor of light hideth thee!",
  "first_line": "Immortal, invisible, God only wise,"
}