{
  "title": "My God, how wonderful thou art",
  "author": "",
  "tune": "St. Etheldreda",
  "number": "31",
  "lyrics": "My God, how wonderful thou art,\nThy majesty how bright!\nHow beautiful thy mercy-seat,\nIn depths of burning light!\n\nHow dread are thine eternal years,\nO everlasting Lord,\nBy holy angels, day and night,\nIncessantly adored!\n\nO how I fear thee, living God,\nWith deepest, tenderest fears;\nAnd worship thee with trembling hope,\nAnd penitential tears.\n\nYet I may love thee too, O Lord,\nAlmighty as thou art;\nFor thou hast stooped to ask of me\nThe love of my poor heart.\n\nNo earthly father loves like thee,\nNo mother half so mild\nBears and forbears, as thou hast done\nWith me, thy sinful child.\n\nHow wonderful, how beautiful,\nThe sight of thee will be,\nThine endless wisdom, boundless power,\nAnd aweful purity!",
  "first_line": "My God, how wonderful thou art,"
}