{
  "title": "Not unto us, O Lord of heaven",
  "author": "",
  "tune": "Gairney Bridge",
  "number": "68",
  "lyrics": "From Psalm 115:1-3, 9-14, 18\n\nNot unto us, O Lord of heav'n,\nBut unto thee be glory given;\nIn love and truth thou dost fulfil\nThe counsels of thy sovereign will;\nThough nations fail thy pow'r to own,\nYet thou dost reign, and thou alone.\n\nLet Israel trust in God alone,\nThe Lord whose grace and power are known;\nTo him your full allegiance yield,\nAnd he will be your help and shield;\nAll those who fear him God will bless,\nHis saints have proved his faithfulness.\n\nAll ye that fear him and adore,\nThe Lord increase you more and more;\nBoth great and small who him confess,\nYou and your children he will bless.\nYea, we will ever bless his Name;\nPraise ye the Lord, his praise proclaim.",
  "first_line": "From Psalm 115:1-3, 9-14, 18"
}