{
  "title": "This is the message that I bring",
  "author": "",
  "tune": "The King's Business",
  "number": "695",
  "lyrics": "I am a stranger here, within a foreign land;\n\nMy home is far away, upon a golden strand;\n\nAmbassador to be of realms beyond the sea,\n\nI'm here on business for my King.\n\n\nThis is the message that I bring,\n\nA message angels fain would sing:\n\n\"Oh, be ye reconciled,\"\n\nThus saith my Lord and King,\n\n\"Oh, be ye reconciled to God.\"\n\n\nThis is the King's command: that all men, ev'rywhere,\n\nRepent and turn away from sin's seductive snare;\n\nThat all who will obey, with him shall reign for aye,\n\nAnd that's my business for my King.\n\n\nMy home is brighter far than Sharon's rosy plain,\n\nEternal life and joy throughout its vast domain;\n\nMy Sovereign bids me tell how mortals there may dwell,\n\nAnd that's my business for my King.",
  "first_line": "I am a stranger here, within a foreign land;"
}